serious_serializers/__init__.py
serious_serializers/serializers.py
serious_serializers-0.1.0.dist-info/METADATA
serious_serializers-0.1.0.dist-info/WHEEL
serious_serializers-0.1.0.dist-info/top_level.txt
serious_serializers-0.1.0.dist-info/RECORD
