Metadata-Version: 2.1
Name: serious-serializers
Version: 0.1.0
Summary: Ordered dataclass serializer mixin for sloted dataclasses
Home-page: https://github.com/sirno/serious_slots
License: MIT
Requires-Dist: pyyaml
Requires-Dist: typing-extensions
Provides-Extra: dev
Requires-Dist: pytest ; extra == 'dev'
Requires-Dist: black ; extra == 'dev'
Requires-Dist: tox ; extra == 'dev'
